mltronsAutoDataPrep/__init__.py
mltronsAutoDataPrep/lib/__init__.py
mltronsAutoDataPrep/lib/v1/__init__.py
mltronsAutoDataPrep/lib/v1/correct_variable_types.py
mltronsAutoDataPrep/lib/v1/dataprep.py
mltronsAutoDataPrep/lib/v1/datetime_formatting.py
mltronsAutoDataPrep/lib/v1/duplication.py
mltronsAutoDataPrep/lib/v1/handle_null_values.py
mltronsAutoDataPrep/lib/v1/logs.py
mltronsAutoDataPrep/lib/v1/read_file_from_local.py
mltronsAutoDataPrep/lib/v1/read_file_from_s3.py
mltronsAutoDataPrep/lib/v1/readfile.py
mltronsAutoDataPrep/lib/v1/save_file.py
mltronsAutoDataPrep/lib/v1/save_file_local.py
mltronsAutoDataPrep/lib/v1/save_file_s3.py
mltronsAutoDataPrep/lib/v1/split_time_variable.py
mltronsAutoDataPrep/lib/v2/__init__.py
mltronsAutoDataPrep/lib/v2/imports.py
mltronsAutoDataPrep/lib/v2/Logger/__init__.py
mltronsAutoDataPrep/lib/v2/Logger/logs.py
mltronsAutoDataPrep/lib/v2/Middlewares/__init__.py
mltronsAutoDataPrep/lib/v2/Middlewares/drop_col_with_null_val.py
mltronsAutoDataPrep/lib/v2/Middlewares/drop_col_with_same_val.py
mltronsAutoDataPrep/lib/v2/Middlewares/dtype_conversion.py
mltronsAutoDataPrep/lib/v2/Middlewares/fetch_datetime_columns.py
mltronsAutoDataPrep/lib/v2/Middlewares/fetch_skewed_columns.py
mltronsAutoDataPrep/lib/v2/Middlewares/fetch_url_columns.py
mltronsAutoDataPrep/lib/v2/Operations/__init__.py
mltronsAutoDataPrep/lib/v2/Operations/read_file_from_local.py
mltronsAutoDataPrep/lib/v2/Operations/read_file_from_s3.py
mltronsAutoDataPrep/lib/v2/Operations/readfile.py
mltronsAutoDataPrep/lib/v2/Operations/save_file.py
mltronsAutoDataPrep/lib/v2/Operations/save_file_local.py
mltronsAutoDataPrep/lib/v2/Operations/save_file_s3.py
mltronsAutoDataPrep/lib/v2/Pipelines/__init__.py
mltronsAutoDataPrep/lib/v2/Pipelines/etl_pipeline.py
mltronsAutoDataPrep/lib/v2/Transformers/__init__.py
mltronsAutoDataPrep/lib/v2/Transformers/change_columns_order.py
mltronsAutoDataPrep/lib/v2/Transformers/convert_nan_to_null.py
mltronsAutoDataPrep-0.0.15.dist-info/METADATA
mltronsAutoDataPrep-0.0.15.dist-info/WHEEL
mltronsAutoDataPrep-0.0.15.dist-info/top_level.txt
mltronsAutoDataPrep-0.0.15.dist-info/RECORD
