Metadata-Version: 2.1
Name: mltronsAutoDataPrep
Version: 0.0.15
Summary: First Automated Data Preparation library powered by Deep Learning to  automatically clean and prepare TBs of data on clusters at scale.
Home-page: https://github.com/ms8909/mltrons-auto-data-prep
Author: Muddassar Sharif
Author-email: ms8909@nyu.edu
License: UNKNOWN
Platform: UNKNOWN
Classifier: Programming Language :: Python :: 3
Classifier: License :: OSI Approved :: MIT License
Classifier: Operating System :: OS Independent
Requires-Dist: pyspark (==2.4.0)
Requires-Dist: numpy (==1.16.4)
Requires-Dist: nltk (==3.4.4)
Requires-Dist: boto3 (==1.9.238)
Requires-Dist: Pattern (==3.6)
Requires-Dist: scipy (==1.2.1)
Requires-Dist: pandas (==0.24.2)
Requires-Dist: datawig (==0.1.10)
Requires-Dist: python-dateutil (==2.8.1)
